sms/__init__.py
sms/base.py
sms/config.py
sms/factory.py
sms_service_aggregator-0.1.0.dist-info/METADATA
sms_service_aggregator-0.1.0.dist-info/RECORD
sms_service_aggregator-0.1.0.dist-info/WHEEL
sms_service_aggregator-0.1.0.dist-info/top_level.txt
